pronoms/__init__.py
pronoms/normalizers/__init__.py
pronoms/normalizers/directlfq_normalizer.py
pronoms/normalizers/l1_normalizer.py
pronoms/normalizers/mad_normalizer.py
pronoms/normalizers/median_normalizer.py
pronoms/normalizers/median_polish_normalizer.py
pronoms/normalizers/quantile_normalizer.py
pronoms/normalizers/splm_normalizer.py
pronoms/normalizers/vsn_normalizer.py
pronoms/utils/__init__.py
pronoms/utils/plotting.py
pronoms/utils/r_interface.py
pronoms/utils/transformations.py
pronoms/utils/validators.py
pronoms-0.1.0.dist-info/licenses/LICENSE
pronoms-0.1.0.dist-info/METADATA
pronoms-0.1.0.dist-info/WHEEL
pronoms-0.1.0.dist-info/top_level.txt
pronoms-0.1.0.dist-info/RECORD
