Metadata-Version: 2.4
Name: pronoms
Version: 0.1.0
Summary: Flexible normalization methods for proteomics quantitative data
Author-email: Michael Riffle <mriffle@uw.edu>
License: MIT
Project-URL: Homepage, https://github.com/mriffle/pronoms
Project-URL: Repository, https://github.com/mriffle/pronoms
Requires-Python: >=3.9
License-File: LICENSE
Requires-Dist: numpy>=1.24
Requires-Dist: pandas>=2.0
Requires-Dist: matplotlib>=3.7
Requires-Dist: rpy2>=3.5
Requires-Dist: scipy>=1.6.0
Requires-Dist: scikit-learn>=0.24.0
Requires-Dist: seaborn>=0.11.0
Requires-Dist: statsmodels>=0.12.0
Requires-Dist: directlfq[dask]>=0.3.2
Provides-Extra: dev
Requires-Dist: pytest>=7.0; extra == "dev"
Requires-Dist: black; extra == "dev"
Requires-Dist: flake8; extra == "dev"
Requires-Dist: jupyter; extra == "dev"
Dynamic: license-file
